[{"inputs":[{"internalType":"address","name":"_owner","type":"address"},{"internalType":"uint256","name":"_id","type":"uint256"}],"name":"balanceOf","outputs":[{"internalType":"uint256","name":"bal_","type":"uint256"}],"stateMutability":"view","type":"function"},{"inputs":[{"internalType":"address[]","name":"_owners","type":"address[]"},{"internalType":"uint256[]","name":"_ids","type":"uint256[]"}],"name":"balanceOfBatch","outputs":[{"internalType":"uint256[]","name":"bals","type":"uint256[]"}],"stateMutability":"view","type":"function"},{"inputs":[{"internalType":"address","name":"account","type":"address"},{"internalType":"address","name":"operator","type":"address"}],"name":"isApprovedForAll","outputs":[{"internalType":"bool","name":"operators_","type":"bool"}],"stateMutability":"view","type":"function"},{"inputs":[{"internalType":"address","name":"_from","type":"address"},{"internalType":"address","name":"_to","type":"address"},{"internalType":"uint256[]","name":"_ids","type":"uint256[]"},{"internalType":"uint256[]","name":"_values","type":"uint256[]"},{"internalType":"bytes","name":"_data","type":"bytes"}],"name":"safeBatchTransferFrom","outputs":[],"stateMutability":"nonpayable","type":"function"},{"inputs":[{"internalType":"address","name":"_from","type":"address"},{"internalType":"address","name":"_to","type":"address"},{"internalType":"uint256","name":"_id","type":"uint256"},{"internalType":"uint256","name":"_value","type":"uint256"},{"internalType":"bytes","name":"_data","type":"bytes"}],"name":"safeTransferFrom","outputs":[],"stateMutability":"nonpayable","type":"function"},{"inputs":[{"internalType":"address","name":"_operator","type":"address"},{"internalType":"bool","name":"_approved","type":"bool"}],"name":"setApprovalForAll","outputs":[],"stateMutability":"nonpayable","type":"function"},{"inputs":[{"internalType":"string","name":"_value","type":"string"}],"name":"setBaseURI","outputs":[],"stateMutability":"nonpayable","type":"function"},{"inputs":[{"internalType":"uint256","name":"_id","type":"uint256"}],"name":"uri","outputs":[{"internalType":"string","name":"","type":"string"}],"stateMutability":"view","type":"function"},{"anonymous":false,"inputs":[{"indexed":false,"internalType":"uint256","name":"_installationId","type":"uint256"}],"name":"AddInstallationType","type":"event"},{"anonymous":false,"inputs":[{"indexed":false,"internalType":"address","name":"_aavegotchiDiamond","type":"address"},{"indexed":false,"internalType":"address","name":"_realmDiamond","type":"address"},{"indexed":false,"internalType":"address","name":"_gltr","type":"address"},{"indexed":false,"internalType":"address","name":"_pixelcraft","type":"address"},{"indexed":false,"internalType":"address","name":"_aavegotchiDAO","type":"address"},{"indexed":false,"internalType":"bytes","name":"_backendPubKey","type":"bytes"}],"name":"AddressesUpdated","type":"event"},{"anonymous":false,"inputs":[{"indexed":false,"internalType":"uint256","name":"_installationId","type":"uint256"}],"name":"DeprecateInstallation","type":"event"},{"anonymous":false,"inputs":[{"indexed":false,"internalType":"uint256","name":"_installationId","type":"uint256"},{"indexed":false,"internalType":"uint256","name":"_newDeprecatetime","type":"uint256"}],"name":"EditDeprecateTime","type":"event"},{"anonymous":false,"inputs":[{"indexed":false,"internalType":"uint256","name":"_installationId","type":"uint256"}],"name":"EditInstallationType","type":"event"},{"anonymous":false,"inputs":[{"indexed":false,"internalType":"uint256","name":"_installationId","type":"uint256"}],"name":"EditInstallationUnequipType","type":"event"},{"anonymous":false,"inputs":[{"indexed":false,"internalType":"uint256","name":"_installationId","type":"uint256"},{"indexed":false,"internalType":"uint256","name":"_unequipType","type":"uint256"}],"name":"SetInstallationUnequipType","type":"event"},{"anonymous":false,"inputs":[{"indexed":true,"internalType":"uint256","name":"_realmId","type":"uint256"},{"indexed":false,"internalType":"uint256","name":"_coordinateX","type":"uint256"},{"indexed":false,"internalType":"uint256","name":"_coordinateY","type":"uint256"},{"indexed":false,"internalType":"uint256","name":"_installationId","type":"uint256"}],"name":"UpgradeCancelled","type":"event"},{"inputs":[{"components":[{"internalType":"uint8","name":"width","type":"uint8"},{"internalType":"uint8","name":"height","type":"uint8"},{"internalType":"uint16","name":"installationType","type":"uint16"},{"internalType":"uint8","name":"level","type":"uint8"},{"internalType":"uint8","name":"alchemicaType","type":"uint8"},{"internalType":"uint32","name":"spillRadius","type":"uint32"},{"internalType":"uint16","name":"spillRate","type":"uint16"},{"internalType":"uint8","name":"upgradeQueueBoost","type":"uint8"},{"internalType":"uint32","name":"craftTime","type":"uint32"},{"internalType":"uint32","name":"nextLevelId","type":"uint32"},{"internalType":"bool","name":"deprecated","type":"bool"},{"internalType":"uint256[4]","name":"alchemicaCost","type":"uint256[4]"},{"internalType":"uint256","name":"harvestRate","type":"uint256"},{"internalType":"uint256","name":"capacity","type":"uint256"},{"internalType":"uint256[]","name":"prerequisites","type":"uint256[]"},{"internalType":"string","name":"name","type":"string"},{"internalType":"uint256","name":"unequipType","type":"uint256"},{"internalType":"uint256","name":"deprecateTime","type":"uint256"}],"internalType":"struct InstallationTypeIO[]","name":"_installationTypes","type":"tuple[]"}],"name":"addInstallationTypes","outputs":[],"stateMutability":"nonpayable","type":"function"},{"inputs":[{"components":[{"internalType":"uint256","name":"_parcelId","type":"uint256"},{"internalType":"uint16","name":"_coordinateX","type":"uint16"},{"internalType":"uint16","name":"_coordinateY","type":"uint16"},{"internalType":"uint256","name":"_installationId","type":"uint256"}],"internalType":"struct InstallationAdminFacet.BuggedUpgradeInput[]","name":"_upgrades","type":"tuple[]"}],"name":"deleteBuggedUpgrades","outputs":[],"stateMutability":"nonpayable","type":"function"},{"inputs":[{"internalType":"bytes32[]","name":"_hashes","type":"bytes32[]"}],"name":"deleteBuggedUpgradesWithHashes","outputs":[],"stateMutability":"nonpayable","type":"function"},{"inputs":[{"internalType":"uint256[]","name":"_installationIds","type":"uint256[]"}],"name":"deprecateInstallations","outputs":[],"stateMutability":"nonpayable","type":"function"},{"inputs":[{"internalType":"uint256","name":"_typeId","type":"uint256"},{"internalType":"uint40","name":"_deprecateTime","type":"uint40"}],"name":"editDeprecateTime","outputs":[],"stateMutability":"nonpayable","type":"function"},{"inputs":[{"internalType":"uint256[]","name":"_ids","type":"uint256[]"},{"components":[{"internalType":"uint8","name":"width","type":"uint8"},{"internalType":"uint8","name":"height","type":"uint8"},{"internalType":"uint16","name":"installationType","type":"uint16"},{"internalType":"uint8","name":"level","type":"uint8"},{"internalType":"uint8","name":"alchemicaType","type":"uint8"},{"internalType":"uint32","name":"spillRadius","type":"uint32"},{"internalType":"uint16","name":"spillRate","type":"uint16"},{"internalType":"uint8","name":"upgradeQueueBoost","type":"uint8"},{"internalType":"uint32","name":"craftTime","type":"uint32"},{"internalType":"uint32","name":"nextLevelId","type":"uint32"},{"internalType":"bool","name":"deprecated","type":"bool"},{"internalType":"uint256[4]","name":"alchemicaCost","type":"uint256[4]"},{"internalType":"uint256","name":"harvestRate","type":"uint256"},{"internalType":"uint256","name":"capacity","type":"uint256"},{"internalType":"uint256[]","name":"prerequisites","type":"uint256[]"},{"internalType":"string","name":"name","type":"string"}],"internalType":"struct InstallationType[]","name":"_installationTypes","type":"tuple[]"}],"name":"editInstallationTypes","outputs":[],"stateMutability":"nonpayable","type":"function"},{"inputs":[{"internalType":"uint256[]","name":"_ids","type":"uint256[]"},{"internalType":"uint256[]","name":"_unequipTypes","type":"uint256[]"}],"name":"editInstallationUnequipTypes","outputs":[],"stateMutability":"nonpayable","type":"function"},{"inputs":[{"components":[{"internalType":"uint256","name":"_parcelId","type":"uint256"},{"internalType":"uint256","name":"_oldAltarId","type":"uint256"},{"internalType":"uint256","name":"_newAltarId","type":"uint256"}],"internalType":"struct InstallationAdminFacet.MissingAltars[]","name":"_altars","type":"tuple[]"}],"name":"fixMissingAltars","outputs":[],"stateMutability":"nonpayable","type":"function"},{"inputs":[],"name":"getAddresses","outputs":[{"internalType":"address","name":"_aavegotchiDiamond","type":"address"},{"internalType":"address","name":"_realmDiamond","type":"address"},{"internalType":"address","name":"_gltr","type":"address"},{"internalType":"address","name":"_pixelcraft","type":"address"},{"internalType":"address","name":"_aavegotchiDAO","type":"address"},{"internalType":"bytes","name":"_backendPubKey","type":"bytes"}],"stateMutability":"view","type":"function"},{"inputs":[{"internalType":"uint256","name":"_parcelId","type":"uint256"},{"internalType":"uint16","name":"_x","type":"uint16"},{"internalType":"uint16","name":"_y","type":"uint16"},{"internalType":"uint256","name":"_installationId","type":"uint256"}],"name":"getUniqueHash","outputs":[{"internalType":"uint256","name":"","type":"uint256"}],"stateMutability":"view","type":"function"},{"inputs":[{"internalType":"uint16[]","name":"_installationIds","type":"uint16[]"},{"internalType":"uint16[]","name":"_amounts","type":"uint16[]"},{"internalType":"address","name":"_toAddress","type":"address"}],"name":"mintInstallations","outputs":[],"stateMutability":"nonpayable","type":"function"},{"inputs":[{"internalType":"address","name":"_aavegotchiDiamond","type":"address"},{"internalType":"address","name":"_realmDiamond","type":"address"},{"internalType":"address","name":"_gltr","type":"address"},{"internalType":"address","name":"_pixelcraft","type":"address"},{"internalType":"address","name":"_aavegotchiDAO","type":"address"},{"internalType":"bytes","name":"_backendPubKey","type":"bytes"}],"name":"setAddresses","outputs":[],"stateMutability":"nonpayable","type":"function"},{"inputs":[{"internalType":"address","name":"_newGameManager","type":"address"},{"internalType":"bool","name":"_active","type":"bool"}],"name":"toggleGameManager","outputs":[],"stateMutability":"nonpayable","type":"function"},{"anonymous":false,"inputs":[{"indexed":true,"internalType":"uint256","name":"_queueId","type":"uint256"},{"indexed":true,"internalType":"uint256","name":"_installationId","type":"uint256"},{"indexed":false,"internalType":"uint256","name":"_readyBlock","type":"uint256"},{"indexed":false,"internalType":"address","name":"_sender","type":"address"}],"name":"AddedToQueue","type":"event"},{"anonymous":false,"inputs":[{"indexed":true,"internalType":"uint256","name":"_queueId","type":"uint256"},{"indexed":false,"internalType":"uint256","name":"_blocksReduced","type":"uint256"}],"name":"CraftTimeReduced","type":"event"},{"anonymous":false,"inputs":[{"indexed":true,"internalType":"uint256","name":"_queueId","type":"uint256"}],"name":"QueueClaimed","type":"event"},{"inputs":[{"internalType":"address","name":"_tokenContract","type":"address"},{"internalType":"uint256","name":"_tokenId","type":"uint256"},{"internalType":"uint256","name":"_id","type":"uint256"}],"name":"balanceOfToken","outputs":[{"internalType":"uint256","name":"value","type":"uint256"}],"stateMutability":"view","type":"function"},{"inputs":[{"components":[{"internalType":"uint16","name":"installationID","type":"uint16"},{"internalType":"uint16","name":"amount","type":"uint16"},{"internalType":"uint40","name":"gltr","type":"uint40"}],"internalType":"struct InstallationFacet.BatchCraftInstallationsInput[]","name":"_inputs","type":"tuple[]"}],"name":"batchCraftInstallations","outputs":[],"stateMutability":"nonpayable","type":"function"},{"inputs":[{"internalType":"uint256[]","name":"_queueIds","type":"uint256[]"}],"name":"claimInstallations","outputs":[],"stateMutability":"nonpayable","type":"function"},{"inputs":[{"internalType":"uint16[]","name":"_installationTypes","type":"uint16[]"},{"internalType":"uint40[]","name":"_gltr","type":"uint40[]"}],"name":"craftInstallations","outputs":[],"stateMutability":"nonpayable","type":"function"},{"inputs":[{"internalType":"address","name":"_owner","type":"address"},{"internalType":"uint256","name":"_realmId","type":"uint256"},{"internalType":"uint256","name":"_installationId","type":"uint256"}],"name":"equipInstallation","outputs":[],"stateMutability":"nonpayable","type":"function"},{"inputs":[{"internalType":"uint256","name":"_altarId","type":"uint256"}],"name":"getAltarLevel","outputs":[{"internalType":"uint256","name":"altarLevel_","type":"uint256"}],"stateMutability":"view","type":"function"},{"inputs":[{"internalType":"address","name":"_owner","type":"address"}],"name":"getCraftQueue","outputs":[{"components":[{"internalType":"address","name":"owner","type":"address"},{"internalType":"uint16","name":"installationType","type":"uint16"},{"internalType":"bool","name":"claimed","type":"bool"},{"internalType":"uint40","name":"readyBlock","type":"uint40"},{"internalType":"uint256","name":"id","type":"uint256"}],"internalType":"struct QueueItem[]","name":"output_","type":"tuple[]"}],"stateMutability":"view","type":"function"},{"inputs":[{"internalType":"uint256","name":"_installationTypeId","type":"uint256"}],"name":"getInstallationType","outputs":[{"components":[{"internalType":"uint8","name":"width","type":"uint8"},{"internalType":"uint8","name":"height","type":"uint8"},{"internalType":"uint16","name":"installationType","type":"uint16"},{"internalType":"uint8","name":"level","type":"uint8"},{"internalType":"uint8","name":"alchemicaType","type":"uint8"},{"internalType":"uint32","name":"spillRadius","type":"uint32"},{"internalType":"uint16","name":"spillRate","type":"uint16"},{"internalType":"uint8","name":"upgradeQueueBoost","type":"uint8"},{"internalType":"uint32","name":"craftTime","type":"uint32"},{"internalType":"uint32","name":"nextLevelId","type":"uint32"},{"internalType":"bool","name":"deprecated","type":"bool"},{"internalType":"uint256[4]","name":"alchemicaCost","type":"uint256[4]"},{"internalType":"uint256","name":"harvestRate","type":"uint256"},{"internalType":"uint256","name":"capacity","type":"uint256"},{"internalType":"uint256[]","name":"prerequisites","type":"uint256[]"},{"internalType":"string","name":"name","type":"string"}],"internalType":"struct InstallationType","name":"installationType","type":"tuple"}],"stateMutability":"view","type":"function"},{"inputs":[{"internalType":"uint256[]","name":"_installationTypeIds","type":"uint256[]"}],"name":"getInstallationTypes","outputs":[{"components":[{"internalType":"uint8","name":"width","type":"uint8"},{"internalType":"uint8","name":"height","type":"uint8"},{"internalType":"uint16","name":"installationType","type":"uint16"},{"internalType":"uint8","name":"level","type":"uint8"},{"internalType":"uint8","name":"alchemicaType","type":"uint8"},{"internalType":"uint32","name":"spillRadius","type":"uint32"},{"internalType":"uint16","name":"spillRate","type":"uint16"},{"internalType":"uint8","name":"upgradeQueueBoost","type":"uint8"},{"internalType":"uint32","name":"craftTime","type":"uint32"},{"internalType":"uint32","name":"nextLevelId","type":"uint32"},{"internalType":"bool","name":"deprecated","type":"bool"},{"internalType":"uint256[4]","name":"alchemicaCost","type":"uint256[4]"},{"internalType":"uint256","name":"harvestRate","type":"uint256"},{"internalType":"uint256","name":"capacity","type":"uint256"},{"internalType":"uint256[]","name":"prerequisites","type":"uint256[]"},{"internalType":"string","name":"name","type":"string"}],"internalType":"struct InstallationType[]","name":"installationTypes_","type":"tuple[]"}],"stateMutability":"view","type":"function"},{"inputs":[{"internalType":"uint256","name":"_installationId","type":"uint256"}],"name":"getInstallationUnequipType","outputs":[{"internalType":"uint256","name":"","type":"uint256"}],"stateMutability":"view","type":"function"},{"inputs":[{"internalType":"uint256","name":"_installationId","type":"uint256"}],"name":"getLodgeLevel","outputs":[{"internalType":"uint256","name":"lodgeLevel_","type":"uint256"}],"stateMutability":"view","type":"function"},{"inputs":[{"internalType":"uint256","name":"_installationId","type":"uint256"}],"name":"getReservoirCapacity","outputs":[{"internalType":"uint256","name":"capacity_","type":"uint256"}],"stateMutability":"view","type":"function"},{"inputs":[{"internalType":"uint256","name":"_installationId","type":"uint256"}],"name":"getReservoirStats","outputs":[{"components":[{"internalType":"uint256","name":"spillRate","type":"uint256"},{"internalType":"uint256","name":"spillRadius","type":"uint256"},{"internalType":"uint256","name":"capacity","type":"uint256"}],"internalType":"struct InstallationFacet.ReservoirStats","name":"reservoirStats_","type":"tuple"}],"stateMutability":"view","type":"function"},{"inputs":[{"internalType":"address","name":"_tokenContract","type":"address"},{"internalType":"uint256","name":"_tokenId","type":"uint256"}],"name":"installationBalancesOfToken","outputs":[{"components":[{"internalType":"uint256","name":"installationId","type":"uint256"},{"internalType":"uint256","name":"balance","type":"uint256"}],"internalType":"struct InstallationFacet.InstallationIdIO[]","name":"bals_","type":"tuple[]"}],"stateMutability":"view","type":"function"},{"inputs":[{"internalType":"address","name":"_tokenContract","type":"address"},{"internalType":"uint256","name":"_tokenId","type":"uint256"},{"internalType":"uint256[]","name":"_ids","type":"uint256[]"}],"name":"installationBalancesOfTokenByIds","outputs":[{"internalType":"uint256[]","name":"","type":"uint256[]"}],"stateMutability":"view","type":"function"},{"inputs":[{"internalType":"address","name":"_tokenContract","type":"address"},{"internalType":"uint256","name":"_tokenId","type":"uint256"}],"name":"installationBalancesOfTokenWithTypes","outputs":[{"components":[{"internalType":"uint256","name":"balance","type":"uint256"},{"internalType":"uint256","name":"itemId","type":"uint256"},{"components":[{"internalType":"uint8","name":"width","type":"uint8"},{"internalType":"uint8","name":"height","type":"uint8"},{"internalType":"uint16","name":"installationType","type":"uint16"},{"internalType":"uint8","name":"level","type":"uint8"},{"internalType":"uint8","name":"alchemicaType","type":"uint8"},{"internalType":"uint32","name":"spillRadius","type":"uint32"},{"internalType":"uint16","name":"spillRate","type":"uint16"},{"internalType":"uint8","name":"upgradeQueueBoost","type":"uint8"},{"internalType":"uint32","name":"craftTime","type":"uint32"},{"internalType":"uint32","name":"nextLevelId","type":"uint32"},{"internalType":"bool","name":"deprecated","type":"bool"},{"internalType":"uint256[4]","name":"alchemicaCost","type":"uint256[4]"},{"internalType":"uint256","name":"harvestRate","type":"uint256"},{"internalType":"uint256","name":"capacity","type":"uint256"},{"internalType":"uint256[]","name":"prerequisites","type":"uint256[]"},{"internalType":"string","name":"name","type":"string"}],"internalType":"struct InstallationType","name":"installationType","type":"tuple"}],"internalType":"struct ItemTypeIO[]","name":"installationBalancesOfTokenWithTypes_","type":"tuple[]"}],"stateMutability":"view","type":"function"},{"inputs":[{"internalType":"address","name":"_account","type":"address"}],"name":"installationsBalances","outputs":[{"components":[{"internalType":"uint256","name":"installationId","type":"uint256"},{"internalType":"uint256","name":"balance","type":"uint256"}],"internalType":"struct InstallationFacet.InstallationIdIO[]","name":"bals_","type":"tuple[]"}],"stateMutability":"view","type":"function"},{"inputs":[{"internalType":"address","name":"_owner","type":"address"}],"name":"installationsBalancesWithTypes","outputs":[{"components":[{"internalType":"uint256","name":"balance","type":"uint256"},{"internalType":"uint256","name":"itemId","type":"uint256"},{"components":[{"internalType":"uint8","name":"width","type":"uint8"},{"internalType":"uint8","name":"height","type":"uint8"},{"internalType":"uint16","name":"installationType","type":"uint16"},{"internalType":"uint8","name":"level","type":"uint8"},{"internalType":"uint8","name":"alchemicaType","type":"uint8"},{"internalType":"uint32","name":"spillRadius","type":"uint32"},{"internalType":"uint16","name":"spillRate","type":"uint16"},{"internalType":"uint8","name":"upgradeQueueBoost","type":"uint8"},{"internalType":"uint32","name":"craftTime","type":"uint32"},{"internalType":"uint32","name":"nextLevelId","type":"uint32"},{"internalType":"bool","name":"deprecated","type":"bool"},{"internalType":"uint256[4]","name":"alchemicaCost","type":"uint256[4]"},{"internalType":"uint256","name":"harvestRate","type":"uint256"},{"internalType":"uint256","name":"capacity","type":"uint256"},{"internalType":"uint256[]","name":"prerequisites","type":"uint256[]"},{"internalType":"string","name":"name","type":"string"}],"internalType":"struct InstallationType","name":"installationType","type":"tuple"}],"internalType":"struct ItemTypeIO[]","name":"output_","type":"tuple[]"}],"stateMutability":"view","type":"function"},{"inputs":[{"internalType":"uint256[]","name":"_queueIds","type":"uint256[]"},{"internalType":"uint40[]","name":"_amounts","type":"uint40[]"}],"name":"reduceCraftTime","outputs":[],"stateMutability":"nonpayable","type":"function"},{"inputs":[{"internalType":"uint256","name":"_id","type":"uint256"}],"name":"spilloverRateAndRadiusOfId","outputs":[{"internalType":"uint256","name":"","type":"uint256"},{"internalType":"uint256","name":"","type":"uint256"}],"stateMutability":"view","type":"function"},{"inputs":[{"internalType":"address","name":"_owner","type":"address"},{"internalType":"uint256","name":"_realmId","type":"uint256"},{"internalType":"uint256","name":"_installationId","type":"uint256"}],"name":"unequipInstallation","outputs":[],"stateMutability":"nonpayable","type":"function"},{"inputs":[{"internalType":"uint256","name":"_queueId","type":"uint256"}],"name":"upgradeComplete","outputs":[{"internalType":"bool","name":"","type":"bool"}],"stateMutability":"view","type":"function"},{"anonymous":false,"inputs":[{"indexed":true,"internalType":"uint256","name":"_queueId","type":"uint256"},{"indexed":true,"internalType":"uint256","name":"_realmId","type":"uint256"},{"indexed":false,"internalType":"uint256","name":"_coordinateX","type":"uint256"},{"indexed":false,"internalType":"uint256","name":"_coordinateY","type":"uint256"},{"indexed":false,"internalType":"uint40","name":"_blocksReduced","type":"uint40"}],"name":"UpgradeTimeReduced","type":"event"},{"inputs":[{"internalType":"uint256[]","name":"_upgradeIndexes","type":"uint256[]"}],"name":"finalizeUpgrades","outputs":[],"stateMutability":"nonpayable","type":"function"},{"inputs":[],"name":"getAllUpgradeQueue","outputs":[{"components":[{"internalType":"address","name":"owner","type":"address"},{"internalType":"uint16","name":"coordinateX","type":"uint16"},{"internalType":"uint16","name":"coordinateY","type":"uint16"},{"internalType":"uint40","name":"readyBlock","type":"uint40"},{"internalType":"bool","name":"claimed","type":"bool"},{"internalType":"uint256","name":"parcelId","type":"uint256"},{"internalType":"uint256","name":"installationId","type":"uint256"}],"internalType":"struct UpgradeQueue[]","name":"","type":"tuple[]"}],"stateMutability":"view","type":"function"},{"inputs":[{"internalType":"uint256","name":"_parcelId","type":"uint256"}],"name":"getParcelUpgradeQueue","outputs":[{"components":[{"internalType":"address","name":"owner","type":"address"},{"internalType":"uint16","name":"coordinateX","type":"uint16"},{"internalType":"uint16","name":"coordinateY","type":"uint16"},{"internalType":"uint40","name":"readyBlock","type":"uint40"},{"internalType":"bool","name":"claimed","type":"bool"},{"internalType":"uint256","name":"parcelId","type":"uint256"},{"internalType":"uint256","name":"installationId","type":"uint256"}],"internalType":"struct UpgradeQueue[]","name":"output_","type":"tuple[]"},{"internalType":"uint256[]","name":"indexes_","type":"uint256[]"}],"stateMutability":"view","type":"function"},{"inputs":[{"internalType":"uint256","name":"_queueId","type":"uint256"}],"name":"getUpgradeQueueId","outputs":[{"components":[{"internalType":"address","name":"owner","type":"address"},{"internalType":"uint16","name":"coordinateX","type":"uint16"},{"internalType":"uint16","name":"coordinateY","type":"uint16"},{"internalType":"uint40","name":"readyBlock","type":"uint40"},{"internalType":"bool","name":"claimed","type":"bool"},{"internalType":"uint256","name":"parcelId","type":"uint256"},{"internalType":"uint256","name":"installationId","type":"uint256"}],"internalType":"struct UpgradeQueue","name":"","type":"tuple"}],"stateMutability":"view","type":"function"},{"inputs":[],"name":"getUpgradeQueueLength","outputs":[{"internalType":"uint256","name":"","type":"uint256"}],"stateMutability":"view","type":"function"},{"inputs":[{"internalType":"address","name":"_owner","type":"address"}],"name":"getUserUpgradeQueue","outputs":[{"components":[{"internalType":"address","name":"owner","type":"address"},{"internalType":"uint16","name":"coordinateX","type":"uint16"},{"internalType":"uint16","name":"coordinateY","type":"uint16"},{"internalType":"uint40","name":"readyBlock","type":"uint40"},{"internalType":"bool","name":"claimed","type":"bool"},{"internalType":"uint256","name":"parcelId","type":"uint256"},{"internalType":"uint256","name":"installationId","type":"uint256"}],"internalType":"struct UpgradeQueue[]","name":"output_","type":"tuple[]"},{"internalType":"uint256[]","name":"indexes_","type":"uint256[]"}],"stateMutability":"view","type":"function"},{"inputs":[{"internalType":"address","name":"_owner","type":"address"}],"name":"getUserUpgradeQueueNew","outputs":[{"components":[{"internalType":"address","name":"owner","type":"address"},{"internalType":"uint16","name":"coordinateX","type":"uint16"},{"internalType":"uint16","name":"coordinateY","type":"uint16"},{"internalType":"uint40","name":"readyBlock","type":"uint40"},{"internalType":"bool","name":"claimed","type":"bool"},{"internalType":"uint256","name":"parcelId","type":"uint256"},{"internalType":"uint256","name":"installationId","type":"uint256"}],"internalType":"struct UpgradeQueue[]","name":"output_","type":"tuple[]"},{"internalType":"uint256[]","name":"indexes_","type":"uint256[]"}],"stateMutability":"view","type":"function"},{"inputs":[{"internalType":"uint256","name":"_parcelId","type":"uint256"},{"internalType":"uint256","name":"_installationId","type":"uint256"},{"internalType":"uint256","name":"_x","type":"uint256"},{"internalType":"uint256","name":"_y","type":"uint256"}],"name":"parcelInstallationUpgrading","outputs":[{"internalType":"bool","name":"","type":"bool"}],"stateMutability":"view","type":"function"},{"inputs":[{"internalType":"uint256","name":"_parcelId","type":"uint256"}],"name":"parcelQueueEmpty","outputs":[{"internalType":"bool","name":"","type":"bool"}],"stateMutability":"view","type":"function"},{"inputs":[{"internalType":"uint256","name":"_upgradeIndex","type":"uint256"},{"internalType":"uint256","name":"_gotchiId","type":"uint256"},{"internalType":"uint40","name":"_blocks","type":"uint40"},{"internalType":"bytes","name":"_signature","type":"bytes"}],"name":"reduceUpgradeTime","outputs":[],"stateMutability":"nonpayable","type":"function"},{"inputs":[{"components":[{"internalType":"address","name":"owner","type":"address"},{"internalType":"uint16","name":"coordinateX","type":"uint16"},{"internalType":"uint16","name":"coordinateY","type":"uint16"},{"internalType":"uint40","name":"readyBlock","type":"uint40"},{"internalType":"bool","name":"claimed","type":"bool"},{"internalType":"uint256","name":"parcelId","type":"uint256"},{"internalType":"uint256","name":"installationId","type":"uint256"}],"internalType":"struct UpgradeQueue","name":"_upgradeQueue","type":"tuple"},{"internalType":"uint256","name":"_gotchiId","type":"uint256"},{"internalType":"bytes","name":"_signature","type":"bytes"},{"internalType":"uint40","name":"_gltr","type":"uint40"}],"name":"upgradeInstallation","outputs":[],"stateMutability":"nonpayable","type":"function"},{"anonymous":false,"inputs":[{"indexed":true,"internalType":"uint256","name":"_realmId","type":"uint256"},{"indexed":true,"internalType":"uint256","name":"_gotchiId","type":"uint256"},{"indexed":true,"internalType":"uint256","name":"_alchemicaType","type":"uint256"},{"indexed":false,"internalType":"uint256","name":"_amount","type":"uint256"},{"indexed":false,"internalType":"uint256","name":"_spilloverRate","type":"uint256"},{"indexed":false,"internalType":"uint256","name":"_spilloverRadius","type":"uint256"}],"name":"AlchemicaClaimed","type":"event"},{"anonymous":false,"inputs":[{"indexed":true,"internalType":"uint256","name":"_eventId","type":"uint256"}],"name":"EventCancelled","type":"event"},{"anonymous":false,"inputs":[{"indexed":true,"internalType":"uint256","name":"_eventId","type":"uint256"},{"indexed":false,"internalType":"uint120","name":"_newPriority","type":"uint120"},{"indexed":false,"internalType":"uint64","name":"_newEndTime","type":"uint64"}],"name":"EventPriorityAndDurationUpdated","type":"event"},{"anonymous":false,"inputs":[{"indexed":true,"internalType":"uint256","name":"_eventId","type":"uint256"},{"components":[{"internalType":"string","name":"title","type":"string"},{"internalType":"uint64","name":"startTime","type":"uint64"},{"internalType":"uint64","name":"endTime","type":"uint64"},{"internalType":"uint120","name":"priority","type":"uint120"},{"internalType":"bool","name":"equipped","type":"bool"},{"internalType":"uint64","name":"lastTimeUpdated","type":"uint64"}],"indexed":false,"internalType":"struct BounceGate","name":"eventDetails","type":"tuple"}],"name":"EventStarted","type":"event"},{"anonymous":false,"inputs":[{"components":[{"internalType":"address","name":"facetAddress","type":"address"},{"internalType":"enum IDiamondCut.FacetCutAction","name":"action","type":"uint8"},{"internalType":"bytes4[]","name":"functionSelectors","type":"bytes4[]"}],"indexed":false,"internalType":"struct IDiamondCut.FacetCut[]","name":"_diamondCut","type":"tuple[]"},{"indexed":false,"internalType":"address","name":"_init","type":"address"},{"indexed":false,"internalType":"bytes","name":"_calldata","type":"bytes"}],"name":"DiamondCut","type":"event"},{"anonymous":false,"inputs":[{"indexed":true,"internalType":"address","name":"previousOwner","type":"address"},{"indexed":true,"internalType":"address","name":"newOwner","type":"address"}],"name":"OwnershipTransferred","type":"event"},{"anonymous":false,"inputs":[{"indexed":true,"internalType":"address","name":"_owner","type":"address"},{"indexed":true,"internalType":"uint256","name":"_installationType","type":"uint256"},{"indexed":false,"internalType":"uint256","name":"_installationId","type":"uint256"}],"name":"MintInstallation","type":"event"},{"anonymous":false,"inputs":[{"indexed":true,"internalType":"address","name":"_owner","type":"address"},{"indexed":true,"internalType":"uint256","name":"_installationId","type":"uint256"},{"indexed":false,"internalType":"uint16","name":"_amount","type":"uint16"}],"name":"MintInstallations","type":"event"},{"anonymous":false,"inputs":[{"indexed":true,"internalType":"address","name":"_owner","type":"address"},{"indexed":true,"internalType":"uint256","name":"_tileType","type":"uint256"},{"indexed":false,"internalType":"uint256","name":"_tileId","type":"uint256"}],"name":"MintTile","type":"event"},{"anonymous":false,"inputs":[{"indexed":true,"internalType":"address","name":"_owner","type":"address"},{"indexed":true,"internalType":"uint256","name":"_tileId","type":"uint256"},{"indexed":false,"internalType":"uint16","name":"_amount","type":"uint16"}],"name":"MintTiles","type":"event"},{"anonymous":false,"inputs":[{"indexed":true,"internalType":"address","name":"_owner","type":"address"},{"indexed":true,"internalType":"address","name":"_approved","type":"address"},{"indexed":true,"internalType":"uint256","name":"_tokenId","type":"uint256"}],"name":"Approval","type":"event"},{"anonymous":false,"inputs":[{"indexed":true,"internalType":"address","name":"_owner","type":"address"},{"indexed":true,"internalType":"uint256","name":"_tokenId","type":"uint256"}],"name":"MintParcel","type":"event"},{"anonymous":false,"inputs":[{"indexed":false,"internalType":"uint256","name":"_realmId","type":"uint256"},{"indexed":false,"internalType":"uint256","name":"_actionRight","type":"uint256"},{"indexed":false,"internalType":"uint256","name":"_accessRight","type":"uint256"}],"name":"ParcelAccessRightSet","type":"event"},{"anonymous":false,"inputs":[{"indexed":true,"internalType":"address","name":"_from","type":"address"},{"indexed":true,"internalType":"address","name":"_to","type":"address"},{"indexed":true,"internalType":"uint256","name":"_tokenId","type":"uint256"}],"name":"Transfer","type":"event"},{"anonymous":false,"inputs":[{"indexed":true,"internalType":"address","name":"_owner","type":"address"},{"indexed":true,"internalType":"address","name":"_operator","type":"address"},{"indexed":false,"internalType":"bool","name":"_approved","type":"bool"}],"name":"ApprovalForAll","type":"event"},{"anonymous":false,"inputs":[{"indexed":true,"internalType":"address","name":"_operator","type":"address"},{"indexed":true,"internalType":"address","name":"_from","type":"address"},{"indexed":true,"internalType":"address","name":"_to","type":"address"},{"indexed":false,"internalType":"uint256[]","name":"_ids","type":"uint256[]"},{"indexed":false,"internalType":"uint256[]","name":"_values","type":"uint256[]"}],"name":"TransferBatch","type":"event"},{"anonymous":false,"inputs":[{"indexed":true,"internalType":"address","name":"_fromContract","type":"address"},{"indexed":true,"internalType":"uint256","name":"_fromTokenId","type":"uint256"},{"indexed":true,"internalType":"uint256","name":"_tokenTypeId","type":"uint256"},{"indexed":false,"internalType":"uint256","name":"_value","type":"uint256"}],"name":"TransferFromParent","type":"event"},{"anonymous":false,"inputs":[{"indexed":true,"internalType":"address","name":"_operator","type":"address"},{"indexed":true,"internalType":"address","name":"_from","type":"address"},{"indexed":true,"internalType":"address","name":"_to","type":"address"},{"indexed":false,"internalType":"uint256","name":"_id","type":"uint256"},{"indexed":false,"internalType":"uint256","name":"_value","type":"uint256"}],"name":"TransferSingle","type":"event"},{"anonymous":false,"inputs":[{"indexed":true,"internalType":"address","name":"_toContract","type":"address"},{"indexed":true,"internalType":"uint256","name":"_toTokenId","type":"uint256"},{"indexed":true,"internalType":"uint256","name":"_tokenTypeId","type":"uint256"},{"indexed":false,"internalType":"uint256","name":"_value","type":"uint256"}],"name":"TransferToParent","type":"event"},{"anonymous":false,"inputs":[{"indexed":false,"internalType":"string","name":"_value","type":"string"},{"indexed":true,"internalType":"uint256","name":"_tokenId","type":"uint256"}],"name":"URI","type":"event"},{"anonymous":false,"inputs":[{"indexed":true,"internalType":"uint256","name":"_realmId","type":"uint256"},{"indexed":false,"internalType":"uint256","name":"_coordinateX","type":"uint256"},{"indexed":false,"internalType":"uint256","name":"_coordinateY","type":"uint256"},{"indexed":false,"internalType":"uint256","name":"_newInstallationId","type":"uint256"}],"name":"UpgradeFinalized","type":"event"},{"anonymous":false,"inputs":[{"indexed":true,"internalType":"uint256","name":"_realmId","type":"uint256"},{"indexed":false,"internalType":"uint256","name":"_coordinateX","type":"uint256"},{"indexed":false,"internalType":"uint256","name":"_coordinateY","type":"uint256"},{"indexed":false,"internalType":"uint256","name":"blockInitiated","type":"uint256"},{"indexed":false,"internalType":"uint256","name":"readyBlock","type":"uint256"},{"indexed":false,"internalType":"uint256","name":"installationId","type":"uint256"}],"name":"UpgradeInitiated","type":"event"},{"anonymous":false,"inputs":[{"indexed":true,"internalType":"address","name":"_owner","type":"address"},{"indexed":true,"internalType":"uint256","name":"_realmId","type":"uint256"},{"indexed":true,"internalType":"uint256","name":"_queueIndex","type":"uint256"}],"name":"UpgradeQueueFinalized","type":"event"},{"anonymous":false,"inputs":[{"indexed":true,"internalType":"address","name":"_owner","type":"address"},{"indexed":true,"internalType":"uint256","name":"_realmId","type":"uint256"},{"indexed":true,"internalType":"uint256","name":"_queueIndex","type":"uint256"}],"name":"UpgradeQueued","type":"event"},{"anonymous":false,"inputs":[{"indexed":false,"internalType":"uint256","name":"_tokenId","type":"uint256"},{"indexed":false,"internalType":"uint256","name":"_round","type":"uint256"},{"indexed":false,"internalType":"uint256[]","name":"_alchemicas","type":"uint256[]"}],"name":"SurveyParcel","type":"event"}]